Metadata-Version: 2.4
Name: myfuntools
Version: 0.6.6
Author: lvxianzhi
Requires-Dist: cffi
Requires-Dist: cryptography
Dynamic: author
